cve_driller/__init__.py
cve_driller/driller.py
cve_driller/common/__init__.py
cve_driller/common/enums.py
cve_driller/patterns/__init__.py
cve_driller/patterns/common.py
cve_driller/patterns/component/__init__.py
cve_driller/patterns/component/configuration/__init__.py
cve_driller/patterns/component/configuration/attacker.py
cve_driller/patterns/component/configuration/cause.py
cve_driller/patterns/component/configuration/condition.py
cve_driller/patterns/component/configuration/weakness.py
cve_driller/patterns/configuration/__init__.py
cve_driller/patterns/configuration/attacker/impact.py
cve_driller/patterns/configuration/cause/attacker.py
cve_driller/patterns/configuration/cause/condition.py
cve_driller/patterns/configuration/cause/vector.py
cve_driller/patterns/configuration/cause/weakness.py
cve_driller/patterns/configuration/condition/cause.py
cve_driller/patterns/configuration/weakness/attacker.py
cve_driller/patterns/configuration/weakness/component.py
cve_driller/patterns/configuration/weakness/condition.py
cve_driller/patterns/weakness/__init__.py
cve_driller/patterns/weakness/component/__init__.py
cve_driller/patterns/weakness/component/configuration.py
cve_driller/patterns/weakness/configuration/__init__.py
cve_driller/patterns/weakness/configuration/attacker.py
cve_driller/patterns/weakness/configuration/cause.py
cve_driller/patterns/weakness/configuration/component.py
cve_driller/patterns/weakness/configuration/condition.py
cve_driller/patterns/weakness/configuration/vector.py
cve_driller-0.2.4.dist-info/licenses/LICENSE
cve_driller-0.2.4.dist-info/METADATA
cve_driller-0.2.4.dist-info/WHEEL
cve_driller-0.2.4.dist-info/top_level.txt
cve_driller-0.2.4.dist-info/RECORD
